hwd/dftm.vhd
-- File: dftm.vhd
-- Generated by MyHDL 0.11
-- Date: Sun May 22 12:03:43 2022


library IEEE;
use IEEE.std_logic_1164.all;
use IEEE.numeric_std.all;
use std.textio.all;

use work.pck_myhdl_011.all;

entity dftm is
    port (
        clk_i: in std_logic;
        host_intf_rst_i: in std_logic;
        host_intf_rd_i: in std_logic;
        host_intf_wr_i: in std_logic;
        host_intf_addr_i: in unsigned(23 downto 0);
        host_intf_data_i: in unsigned(15 downto 0);
        host_intf_data_o: out unsigned(15 downto 0);
        host_intf_done_o: out std_logic;
        host_intf_rdPending_o: in std_logic;
        host_intf_dftm_i: in std_logic;
        host_intf_sdram_rst_i: in std_logic;
        host_intf_sdram_rd_i: out std_logic;
        host_intf_sdram_wr_i: out std_logic;
        host_intf_sdram_addr_i: inout unsigned(23 downto 0);
        host_intf_sdram_data_i: out unsigned(15 downto 0);
        host_intf_sdram_data_o: inout unsigned(15 downto 0);
        host_intf_sdram_done_o: in std_logic;
        host_intf_sdram_rdPending_o: in std_logic;
        host_intf_sdram_dftm_i: in std_logic
    );
end entity dftm;


architecture MyHDL of dftm is


type t_enum_OPERATION_MODE_1 is (
	NORMAL,
	RECODING_UP,
	RECODING_DOWN
	);
type t_enum_RECODING_MODE_2 is (
	READ,
	WAIT_READ,
	WRITE,
	WAIT_WRITE,
	WAIT_WRITE_1,
	WAIT_WRITE_2
	);

signal current_operation_mode: t_enum_OPERATION_MODE_1;
signal current_recoding_mode: t_enum_RECODING_MODE_2;
signal in_read: std_logic;
signal iram_send: std_logic;
signal recode_address: unsigned(23 downto 0);
signal recode_count: unsigned(15 downto 0);
signal recode_data_o: unsigned(15 downto 0);
signal recode_from_ecc: unsigned(2 downto 0);
signal recode_original_data: unsigned(15 downto 0);
signal recode_position: unsigned(15 downto 0);
signal recode_to_ecc: unsigned(2 downto 0);
type t_array_ram is array(0 to 256-1) of unsigned(2 downto 0);
signal ram: t_array_ram;

function MYHDL2_get_position(
    addr: in unsigned;
    page_size: in natural
    ) return integer is
begin
    return to_integer(addr / page_size);
end function MYHDL2_get_position;

function MYHDL3_get_configuration(
    mem: in unsigned
    ) return integer is
begin
    return to_integer((mem and to_unsigned(1, 3)));
end function MYHDL3_get_configuration;

function MYHDL4_get_encode(
    mem: in unsigned
    ) return integer is
begin
    return to_integer(shift_right(mem, 1));
end function MYHDL4_get_encode;

function MYHDL5_decoder_check(
    data: in std_logic;
    type: in integer
    ) return std_logic is
begin
    return '1';
end function MYHDL5_decoder_check;

function MYHDL6_decoder(
    data: in unsigned;
    type: in integer
    ) return unsigned is
begin
    return data;
end function MYHDL6_decoder;

function MYHDL7_get_next_encode(
    enc: in integer
    ) return integer is
    variable L: line;
    variable LAST_ENCODE: natural;
begin
    LAST_ENCODE := 3;
    if (enc >= 3) then
        write(L, string'("more:"));
        write(L, string'(" "));
        write(L, to_string(enc));
        writeline(output, L);
        return enc;
    else
        write(L, string'("enc+1:"));
        write(L, string'(" "));
        write(L, to_string(enc));
        writeline(output, L);
        return (enc + 1);
    end if;
end function MYHDL7_get_next_encode;

function MYHDL8_decoder(
    data: in unsigned;
    type: in integer
    ) return unsigned is
begin
    return data;
end function MYHDL8_decoder;

function MYHDL9_decoder(
    data: in unsigned;
    type: in unsigned
    ) return unsigned is
begin
    return data;
end function MYHDL9_decoder;

function MYHDL11_decoder(
    data: in unsigned;
    type: in unsigned
    ) return unsigned is
begin
    return data;
end function MYHDL11_decoder;

function MYHDL12_encoder(
    data: in unsigned;
    type: in unsigned
    ) return unsigned is
begin
    return data;
end function MYHDL12_encoder;

procedure MYHDL13_set_encode(
    signal mem: out unsigned;
    signal enc: in unsigned) is
begin
    mem(1) <= (enc and to_unsigned(1, 3))(0);
    mem(2) <= shift_right((enc and to_unsigned(2, 3)), 1)(0);
end procedure MYHDL13_set_encode;

begin




DFTM_MAIN: process (clk_i) is
    variable L: line;
    variable iram_current_position: integer;
    variable current_encode: integer;
    variable is_dynamic: integer;
    variable ram_inf: unsigned(2 downto 0);
    variable decode_ok: std_logic;
    variable next_encode: integer;
    variable recode: std_logic;
    variable recoding_current_address: integer;
    variable r_count: integer;
begin
    if rising_edge(clk_i) then
        if (current_operation_mode = NORMAL) then
            if bool(host_intf_dftm_i) then
                if bool(iram_send) then
                    host_intf_done_o <= '1';
                    iram_send <= '0';
                else
                    if bool(host_intf_rd_i) then
                        host_intf_data_o <= resize(ram(to_integer(host_intf_addr_i)), 16);
                        host_intf_done_o <= '0';
                        iram_send <= '1';
                    end if;
                    if bool(host_intf_wr_i) then
                        ram(to_integer(host_intf_addr_i)) <= to_unsigned(to_integer(host_intf_data_i), 3);
                        write(L, string'("WR"));
                        write(L, string'(" "));
                        write(L, to_hstring(host_intf_addr_i));
                        write(L, string'(" "));
                        write(L, string'("-"));
                        write(L, string'(" "));
                        write(L, to_hstring(host_intf_data_i));
                        writeline(output, L);
                        host_intf_done_o <= '0';
                        iram_send <= '1';
                    end if;
                end if;
            else
                iram_current_position := MYHDL2_get_position(host_intf_addr_i, 256);
                current_encode := 0;
                is_dynamic := 0;
                -- Accessing a area major than managed, we will read without encode
                if (iram_current_position < 256) then
                    ram_inf := ram(iram_current_position);
                    is_dynamic := MYHDL3_get_configuration(ram_inf);
                    is_dynamic := 1;
                    current_encode := MYHDL4_get_encode(ram_inf);
                end if;
                host_intf_sdram_addr_i <= host_intf_addr_i;
                host_intf_sdram_rd_i <= host_intf_rd_i;
                host_intf_sdram_wr_i <= host_intf_wr_i;
                host_intf_sdram_data_i <= host_intf_data_i;
                if (host_intf_sdram_rdPending_o = '1') then
                    in_read <= '1';
                end if;
                if bool(host_intf_sdram_done_o) then
                    if (in_read = '0') then
                        host_intf_done_o <= host_intf_sdram_done_o;
                    else
                        in_read <= '0';
                        decode_ok := MYHDL5_decoder_check(host_intf_sdram_done_o, current_encode);
                        if (host_intf_addr_i = 120) then
                            decode_ok := '0';
                        end if;
                        if bool(decode_ok) then
                            host_intf_data_o <= MYHDL6_decoder(host_intf_sdram_data_o, current_encode);
                            host_intf_done_o <= host_intf_sdram_done_o;
                        else
                            next_encode := MYHDL7_get_next_encode(current_encode);
                            recode := stdl((next_encode /= current_encode) and (is_dynamic = 1));
                            write(L, string'("will recode:"));
                            write(L, string'(" "));
                            write(L, to_string(bool(recode)));
                            writeline(output, L);
                            write(L, string'("Code?:"));
                            write(L, string'(" "));
                            write(L, to_string((next_encode /= current_encode)));
                            writeline(output, L);
                            write(L, string'("Dyn?:"));
                            write(L, string'(" "));
                            write(L, to_string(is_dynamic));
                            writeline(output, L);
                            if bool(recode) then
                                current_operation_mode <= RECODING_UP;
                                current_recoding_mode <= READ;
                                recode_position <= to_unsigned(iram_current_position, 16);
                                recode_address <= host_intf_addr_i;
                                recode_from_ecc <= to_unsigned(current_encode, 3);
                                recode_to_ecc <= to_unsigned(next_encode, 3);
                                recode_count <= to_unsigned(0, 16);
                                host_intf_done_o <= '0';
                                host_intf_sdram_rd_i <= '0';
                            else
                                host_intf_data_o <= MYHDL8_decoder(host_intf_sdram_data_o, current_encode);
                                host_intf_done_o <= host_intf_sdram_done_o;
                                in_read <= '0';
                            end if;
                        end if;
                    end if;
                else
                    host_intf_done_o <= host_intf_sdram_done_o;
                end if;
            end if;
        else
            if ((recode_count = 0) and (current_recoding_mode = READ)) then
                write(L, string'("STARTING RECODING pos:"));
                write(L, string'(" "));
                write(L, to_hstring(recode_position));
                write(L, string'(" "));
                write(L, string'(", FROM ECC "));
                write(L, string'(" "));
                write(L, to_hstring(recode_from_ecc));
                write(L, string'(" "));
                write(L, string'(", to:"));
                write(L, string'(" "));
                write(L, to_hstring(recode_to_ecc));
                writeline(output, L);
            end if;
            recoding_current_address := to_integer((recode_position * 256) + recode_count);
            write(L, string'("RECODING "));
            write(L, string'(" "));
            write(L, to_hstring(recode_position));
            write(L, string'(" "));
            write(L, string'(" - "));
            write(L, string'(" "));
            write(L, to_hstring(recode_count));
            write(L, string'(" "));
            write(L, string'(" - "));
            write(L, string'(" "));
            write(L, to_string(recoding_current_address));
            writeline(output, L);
            if (current_recoding_mode = READ) then
                write(L, to_string(current_recoding_mode));
                write(L, string'(" "));
                write(L, to_string(recoding_current_address));
                writeline(output, L);
                host_intf_sdram_addr_i <= to_unsigned(recoding_current_address, 24);
                host_intf_sdram_rd_i <= '1';
                current_recoding_mode <= WAIT_READ;
            end if;
            if (current_recoding_mode = WAIT_READ) then
                host_intf_sdram_rd_i <= '0';
                write(L, to_string(current_recoding_mode));
                writeline(output, L);
                if bool(host_intf_sdram_done_o) then
                    current_recoding_mode <= WRITE;
                    recode_data_o <= MYHDL9_decoder(host_intf_sdram_data_o, recode_from_ecc);
                    recode_data_o <= to_unsigned(to_integer(MYHDL11_decoder(host_intf_sdram_data_o, recode_from_ecc)) + 1, 16);
                    if (recode_address = host_intf_sdram_addr_i) then
                        recode_original_data <= host_intf_sdram_data_o;
                    end if;
                    -- TODO IGNORING THE DECODE ERROR - Having not todo here ... 
                    write(L, string'("RECODING READ "));
                    write(L, string'(" "));
                    write(L, to_hstring(host_intf_sdram_data_o));
                    writeline(output, L);
                end if;
            end if;
            if (current_recoding_mode = WRITE) then
                write(L, to_string(current_recoding_mode));
                writeline(output, L);
                host_intf_sdram_addr_i <= to_unsigned(recoding_current_address, 24);
                host_intf_sdram_data_i <= MYHDL12_encoder(recode_data_o, recode_to_ecc);
                write(L, string'("RECODING WRITE "));
                write(L, string'(" "));
                write(L, to_hstring(host_intf_sdram_data_o));
                writeline(output, L);
                current_recoding_mode <= WAIT_WRITE;
            end if;
            if (current_recoding_mode = WAIT_WRITE) then
                write(L, to_string(current_recoding_mode));
                writeline(output, L);
                host_intf_sdram_wr_i <= '1';
                if bool(host_intf_sdram_done_o) then
                    host_intf_sdram_rd_i <= '0';
                    host_intf_sdram_wr_i <= '0';
                    r_count := to_integer(recode_count + 1);
                    if (r_count < 256) then
                        current_recoding_mode <= WAIT_WRITE_1;
                        recode_count <= to_unsigned(r_count, 16);
                    else
                        -- RECODING DONE
                        host_intf_data_o <= recode_original_data;
                        host_intf_sdram_data_o <= recode_original_data;
                        host_intf_done_o <= '1';
                        current_operation_mode <= NORMAL;
                        ram_inf := ram(to_integer(recode_position));
                        MYHDL13_set_encode(ram_inf, recode_to_ecc);
                        write(L, string'("Change encode pos:"));
                        write(L, string'(" "));
                        write(L, to_hstring(recode_position));
                        write(L, string'(" "));
                        write(L, string'(", from:"));
                        write(L, string'(" "));
                        write(L, to_hstring(recode_from_ecc));
                        write(L, string'(" "));
                        write(L, string'(",to:"));
                        write(L, string'(" "));
                        write(L, to_hstring(recode_to_ecc));
                        writeline(output, L);
                    end if;
                end if;
            end if;
            -- Need wait 2 cycle to wait the WRITE really happen
            if (current_recoding_mode = WAIT_WRITE_1) then
                current_recoding_mode <= WAIT_WRITE_2;
            end if;
            if (current_recoding_mode = WAIT_WRITE_2) then
                current_recoding_mode <= READ;
            end if;
        end if;
    end if;
end process DFTM_MAIN;

end architecture MyHDL;

hwd/dftm.vcd
$date
    Sun May 22 12:47:10 2022
$end
$version
    MyHDL 0.11
$end
$timescale
    1ns
$end

$scope module dftm $end
$var reg 1 ! clk_i $end
$var string 2 " current_operation_mode $end
$var string 3 # current_recoding_mode $end
$var reg 1 $ in_read $end
$var reg 1 % iram_send $end
$var reg 24 & recode_address $end
$var reg 16 ' recode_count $end
$var reg 16 ( recode_data_o $end
$var reg 3 ) recode_from_ecc $end
$var reg 16 * recode_original_data $end
$var reg 16 + recode_position $end
$var reg 3 , recode_to_ecc $end
$var reg 1 - host_intf_dftm_i $end
$var reg 1 . host_intf_done_o $end
$var reg 1 / host_intf_rd_i $end
$var reg 16 0 host_intf_data_o $end
$var reg 24 1 host_intf_addr_i $end
$var reg 1 2 host_intf_wr_i $end
$var reg 16 3 host_intf_data_i $end
$var reg 24 4 host_intf_sdram_addr_i $end
$var reg 1 5 host_intf_sdram_rd_i $end
$var reg 1 6 host_intf_sdram_wr_i $end
$var reg 16 7 host_intf_sdram_data_i $end
$var reg 1 8 host_intf_sdram_rdPending_o $end
$var reg 1 9 host_intf_sdram_done_o $end
$var reg 16 : host_intf_sdram_data_o $end
$scope module ram $end
$var reg 3 ; ram(0) $end
$var reg 3 < ram(1) $end
$var reg 3 = ram(2) $end
$var reg 3 > ram(3) $end
$var reg 3 ? ram(4) $end
$var reg 3 @ ram(5) $end
$var reg 3 A ram(6) $end
$var reg 3 B ram(7) $end
$var reg 3 C ram(8) $end
$var reg 3 D ram(9) $end
$var reg 3 E ram(10) $end
$var reg 3 F ram(11) $end
$var reg 3 G ram(12) $end
$var reg 3 H ram(13) $end
$var reg 3 I ram(14) $end
$var reg 3 J ram(15) $end
$var reg 3 K ram(16) $end
$var reg 3 L ram(17) $end
$var reg 3 M ram(18) $end
$var reg 3 N ram(19) $end
$var reg 3 O ram(20) $end
$var reg 3 P ram(21) $end
$var reg 3 Q ram(22) $end
$var reg 3 R ram(23) $end
$var reg 3 S ram(24) $end
$var reg 3 T ram(25) $end
$var reg 3 U ram(26) $end
$var reg 3 V ram(27) $end
$var reg 3 W ram(28) $end
$var reg 3 X ram(29) $end
$var reg 3 Y ram(30) $end
$var reg 3 Z ram(31) $end
$var reg 3 [ ram(32) $end
$var reg 3 \ ram(33) $end
$var reg 3 ] ram(34) $end
$var reg 3 ^ ram(35) $end
$var reg 3 _ ram(36) $end
$var reg 3 ` ram(37) $end
$var reg 3 a ram(38) $end
$var reg 3 b ram(39) $end
$var reg 3 c ram(40) $end
$var reg 3 d ram(41) $end
$var reg 3 e ram(42) $end
$var reg 3 f ram(43) $end
$var reg 3 g ram(44) $end
$var reg 3 h ram(45) $end
$var reg 3 i ram(46) $end
$var reg 3 j ram(47) $end
$var reg 3 k ram(48) $end
$var reg 3 l ram(49) $end
$var reg 3 m ram(50) $end
$var reg 3 n ram(51) $end
$var reg 3 o ram(52) $end
$var reg 3 p ram(53) $end
$var reg 3 q ram(54) $end
$var reg 3 r ram(55) $end
$var reg 3 s ram(56) $end
$var reg 3 t ram(57) $end
$var reg 3 u ram(58) $end
$var reg 3 v ram(59) $end
$var reg 3 w ram(60) $end
$var reg 3 x ram(61) $end
$var reg 3 y ram(62) $end
$var reg 3 z ram(63) $end
$var reg 3 { ram(64) $end
$var reg 3 | ram(65) $end
$var reg 3 } ram(66) $end
$var reg 3 ~ ram(67) $end
$var reg 3 "! ram(68) $end
$var reg 3 "" ram(69) $end
$var reg 3 "# ram(70) $end
$var reg 3 "$ ram(71) $end
$var reg 3 "% ram(72) $end
$var reg 3 "& ram(73) $end
$var reg 3 "' ram(74) $end
$var reg 3 "( ram(75) $end
$var reg 3 ") ram(76) $end
$var reg 3 "* ram(77) $end
$var reg 3 "+ ram(78) $end
$var reg 3 ", ram(79) $end
$var reg 3 "- ram(80) $end
$var reg 3 ". ram(81) $end
$var reg 3 "/ ram(82) $end
$var reg 3 "0 ram(83) $end
$var reg 3 "1 ram(84) $end
$var reg 3 "2 ram(85) $end
$var reg 3 "3 ram(86) $end
$var reg 3 "4 ram(87) $end
$var reg 3 "5 ram(88) $end
$var reg 3 "6 ram(89) $end
$var reg 3 "7 ram(90) $end
$var reg 3 "8 ram(91) $end
$var reg 3 "9 ram(92) $end
$var reg 3 ": ram(93) $end
$var reg 3 "; ram(94) $end
$var reg 3 "< ram(95) $end
$var reg 3 "= ram(96) $end
$var reg 3 "> ram(97) $end
$var reg 3 "? ram(98) $end
$var reg 3 "@ ram(99) $end
$var reg 3 "A ram(100) $end
$var reg 3 "B ram(101) $end
$var reg 3 "C ram(102) $end
$var reg 3 "D ram(103) $end
$var reg 3 "E ram(104) $end
$var reg 3 "F ram(105) $end
$var reg 3 "G ram(106) $end
$var reg 3 "H ram(107) $end
$var reg 3 "I ram(108) $end
$var reg 3 "J ram(109) $end
$var reg 3 "K ram(110) $end
$var reg 3 "L ram(111) $end
$var reg 3 "M ram(112) $end
$var reg 3 "N ram(113) $end
$var reg 3 "O ram(114) $end
$var reg 3 "P ram(115) $end
$var reg 3 "Q ram(116) $end
$var reg 3 "R ram(117) $end
$var reg 3 "S ram(118) $end
$var reg 3 "T ram(119) $end
$var reg 3 "U ram(120) $end
$var reg 3 "V ram(121) $end
$var reg 3 "W ram(122) $end
$var reg 3 "X ram(123) $end
$var reg 3 "Y ram(124) $end
$var reg 3 "Z ram(125) $end
$var reg 3 "[ ram(126) $end
$var reg 3 "\ ram(127) $end
$var reg 3 "] ram(128) $end
$var reg 3 "^ ram(129) $end
$var reg 3 "_ ram(130) $end
$var reg 3 "` ram(131) $end
$var reg 3 "a ram(132) $end
$var reg 3 "b ram(133) $end
$var reg 3 "c ram(134) $end
$var reg 3 "d ram(135) $end
$var reg 3 "e ram(136) $end
$var reg 3 "f ram(137) $end
$var reg 3 "g ram(138) $end
$var reg 3 "h ram(139) $end
$var reg 3 "i ram(140) $end
$var reg 3 "j ram(141) $end
$var reg 3 "k ram(142) $end
$var reg 3 "l ram(143) $end
$var reg 3 "m ram(144) $end
$var reg 3 "n ram(145) $end
$var reg 3 "o ram(146) $end
$var reg 3 "p ram(147) $end
$var reg 3 "q ram(148) $end
$var reg 3 "r ram(149) $end
$var reg 3 "s ram(150) $end
$var reg 3 "t ram(151) $end
$var reg 3 "u ram(152) $end
$var reg 3 "v ram(153) $end
$var reg 3 "w ram(154) $end
$var reg 3 "x ram(155) $end
$var reg 3 "y ram(156) $end
$var reg 3 "z ram(157) $end
$var reg 3 "{ ram(158) $end
$var reg 3 "| ram(159) $end
$var reg 3 "} ram(160) $end
$var reg 3 "~ ram(161) $end
$var reg 3 #! ram(162) $end
$var reg 3 #" ram(163) $end
$var reg 3 ## ram(164) $end
$var reg 3 #$ ram(165) $end
$var reg 3 #% ram(166) $end
$var reg 3 #& ram(167) $end
$var reg 3 #' ram(168) $end
$var reg 3 #( ram(169) $end
$var reg 3 #) ram(170) $end
$var reg 3 #* ram(171) $end
$var reg 3 #+ ram(172) $end
$var reg 3 #, ram(173) $end
$var reg 3 #- ram(174) $end
$var reg 3 #. ram(175) $end
$var reg 3 #/ ram(176) $end
$var reg 3 #0 ram(177) $end
$var reg 3 #1 ram(178) $end
$var reg 3 #2 ram(179) $end
$var reg 3 #3 ram(180) $end
$var reg 3 #4 ram(181) $end
$var reg 3 #5 ram(182) $end
$var reg 3 #6 ram(183) $end
$var reg 3 #7 ram(184) $end
$var reg 3 #8 ram(185) $end
$var reg 3 #9 ram(186) $end
$var reg 3 #: ram(187) $end
$var reg 3 #; ram(188) $end
$var reg 3 #< ram(189) $end
$var reg 3 #= ram(190) $end
$var reg 3 #> ram(191) $end
$var reg 3 #? ram(192) $end
$var reg 3 #@ ram(193) $end
$var reg 3 #A ram(194) $end
$var reg 3 #B ram(195) $end
$var reg 3 #C ram(196) $end
$var reg 3 #D ram(197) $end
$var reg 3 #E ram(198) $end
$var reg 3 #F ram(199) $end
$var reg 3 #G ram(200) $end
$var reg 3 #H ram(201) $end
$var reg 3 #I ram(202) $end
$var reg 3 #J ram(203) $end
$var reg 3 #K ram(204) $end
$var reg 3 #L ram(205) $end
$var reg 3 #M ram(206) $end
$var reg 3 #N ram(207) $end
$var reg 3 #O ram(208) $end
$var reg 3 #P ram(209) $end
$var reg 3 #Q ram(210) $end
$var reg 3 #R ram(211) $end
$var reg 3 #S ram(212) $end
$var reg 3 #T ram(213) $end
$var reg 3 #U ram(214) $end
$var reg 3 #V ram(215) $end
$var reg 3 #W ram(216) $end
$var reg 3 #X ram(217) $end
$var reg 3 #Y ram(218) $end
$var reg 3 #Z ram(219) $end
$var reg 3 #[ ram(220) $end
$var reg 3 #\ ram(221) $end
$var reg 3 #] ram(222) $end
$var reg 3 #^ ram(223) $end
$var reg 3 #_ ram(224) $end
$var reg 3 #` ram(225) $end
$var reg 3 #a ram(226) $end
$var reg 3 #b ram(227) $end
$var reg 3 #c ram(228) $end
$var reg 3 #d ram(229) $end
$var reg 3 #e ram(230) $end
$var reg 3 #f ram(231) $end
$var reg 3 #g ram(232) $end
$var reg 3 #h ram(233) $end
$var reg 3 #i ram(234) $end
$var reg 3 #j ram(235) $end
$var reg 3 #k ram(236) $end
$var reg 3 #l ram(237) $end
$var reg 3 #m ram(238) $end
$var reg 3 #n ram(239) $end
$var reg 3 #o ram(240) $end
$var reg 3 #p ram(241) $end
$var reg 3 #q ram(242) $end
$var reg 3 #r ram(243) $end
$var reg 3 #s ram(244) $end
$var reg 3 #t ram(245) $end
$var reg 3 #u ram(246) $end
$var reg 3 #v ram(247) $end
$var reg 3 #w ram(248) $end
$var reg 3 #x ram(249) $end
$var reg 3 #y ram(250) $end
$var reg 3 #z ram(251) $end
$var reg 3 #{ ram(252) $end
$var reg 3 #| ram(253) $end
$var reg 3 #} ram(254) $end
$var reg 3 #~ ram(255) $end
$upscope $end
$upscope $end

$enddefinitions $end
$dumpvars
0!
sNORMAL "
sREAD #
0$
0%
b000000000000000000000000 &
b0000000000000000 '
b0000000000000000 (
b000 )
b0000000000000000 *
b0000000000000000 +
b000 ,
0-
0.
0/
b0000000000000000 0
b000000000000000000000000 1
02
b0000000000000000 3
b000000000000000000000000 4
05
06
b0000000000000000 7
08
09
b0000000000000000 :
b000 ;
b000 <
b000 =
b000 >
b000 ?
b000 @
b000 A
b000 B
b000 C
b000 D
b000 E
b000 F
b000 G
b000 H
b000 I
b000 J
b000 K
b000 L
b000 M
b000 N
b000 O
b000 P
b000 Q
b000 R
b000 S
b000 T
b000 U
b000 V
b000 W
b000 X
b000 Y
b000 Z
b000 [
b000 \
b000 ]
b000 ^
b000 _
b000 `
b000 a
b000 b
b000 c
b000 d
b000 e
b000 f
b000 g
b000 h
b000 i
b000 j
b000 k
b000 l
b000 m
b000 n
b000 o
b000 p
b000 q
b000 r
b000 s
b000 t
b000 u
b000 v
b000 w
b000 x
b000 y
b000 z
b000 {
b000 |
b000 }
b000 ~
b000 "!
b000 ""
b000 "#
b000 "$
b000 "%
b000 "&
b000 "'
b000 "(
b000 ")
b000 "*
b000 "+
b000 ",
b000 "-
b000 ".
b000 "/
b000 "0
b000 "1
b000 "2
b000 "3
b000 "4
b000 "5
b000 "6
b000 "7
b000 "8
b000 "9
b000 ":
b000 ";
b000 "<
b000 "=
b000 ">
b000 "?
b000 "@
b000 "A
b000 "B
b000 "C
b000 "D
b000 "E
b000 "F
b000 "G
b000 "H
b000 "I
b000 "J
b000 "K
b000 "L
b000 "M
b000 "N
b000 "O
b000 "P
b000 "Q
b000 "R
b000 "S
b000 "T
b000 "U
b000 "V
b000 "W
b000 "X
b000 "Y
b000 "Z
b000 "[
b000 "\
b000 "]
b000 "^
b000 "_
b000 "`
b000 "a
b000 "b
b000 "c
b000 "d
b000 "e
b000 "f
b000 "g
b000 "h
b000 "i
b000 "j
b000 "k
b000 "l
b000 "m
b000 "n
b000 "o
b000 "p
b000 "q
b000 "r
b000 "s
b000 "t
b000 "u
b000 "v
b000 "w
b000 "x
b000 "y
b000 "z
b000 "{
b000 "|
b000 "}
b000 "~
b000 #!
b000 #"
b000 ##
b000 #$
b000 #%
b000 #&
b000 #'
b000 #(
b000 #)
b000 #*
b000 #+
b000 #,
b000 #-
b000 #.
b000 #/
b000 #0
b000 #1
b000 #2
b000 #3
b000 #4
b000 #5
b000 #6
b000 #7
b000 #8
b000 #9
b000 #:
b000 #;
b000 #<
b000 #=
b000 #>
b000 #?
b000 #@
b000 #A
b000 #B
b000 #C
b000 #D
b000 #E
b000 #F
b000 #G
b000 #H
b000 #I
b000 #J
b000 #K
b000 #L
b000 #M
b000 #N
b000 #O
b000 #P
b000 #Q
b000 #R
b000 #S
b000 #T
b000 #U
b000 #V
b000 #W
b000 #X
b000 #Y
b000 #Z
b000 #[
b000 #\
b000 #]
b000 #^
b000 #_
b000 #`
b000 #a
b000 #b
b000 #c
b000 #d
b000 #e
b000 #f
b000 #g
b000 #h
b000 #i
b000 #j
b000 #k
b000 #l
b000 #m
b000 #n
b000 #o
b000 #p
b000 #q
b000 #r
b000 #s
b000 #t
b000 #u
b000 #v
b000 #w
b000 #x
b000 #y
b000 #z
b000 #{
b000 #|
b000 #}
b000 #~
$end
#1
1!
#2
0!
#3
1!
#4
0!
#5
1!
#6
0!
#7
1!
#8
0!
#9
1!
#10
0!
#11
1!
#12
0!
#13
1!
#14
0!
#15
1!
#16
0!
#17
1!
#18
0!
#19
1!
#20
0!
#21
1!
#22
0!
#23
1!
#24
0!
#25
1!
#26
0!
#27
1!
#28
0!
#29
1!
#30
0!
#31
1!
#32
0!
#33
1!
#34
0!
#35
1!
#36
0!
#37
1!
#38
0!
#39
1!
#40
0!
#41
1!
#42
0!
#43
1!
#44
0!
#45
1!
#46
0!
#47
1!
#48
0!
#49
1!
#50
0!
#51
1!
#52
0!
#53
1!
#54
0!
#55
1!
#56
0!
#57
1!
#58
0!
#59
1!
#60
0!
#61
1!
#62
0!
#63
1!
#64
0!
#65
1!
#66
0!
#67
1!
#68
0!
#69
1!
#70
0!
#71
1!
#72
0!
#73
1!
#74
0!
#75
1!
#76
0!
#77
1!
#78
0!
#79
1!
#80
0!
#81
1!
#82
0!
#83
1!
#84
0!
#85
1!
#86
0!
#87
1!
#88
0!
#89
1!
#90
0!
#91
1!
#92
0!
#93
1!
#94
0!
#95
1!
#96
0!
#97
1!
#98
0!
#99
1!
#100
0!
#101
1!
#102
0!
#103
1!
#104
0!
#105
1!
#106
0!
#107
1!
#108
0!
#109
1!
#110
0!
#111
1!
#112
0!
#113
1!
#114
0!
#115
1!
#116
0!
#117
1!
#118
0!
#119
1!
#120
0!
#121
1!
#122
0!
#123
1!
#124
0!
#125
1!
#126
0!
#127
1!
#128
0!
#129
1!
#130
0!
#131
1!
#132
0!
#133
1!
#134
0!
#135
1!
#136
0!
#137
1!
#138
0!
#139
1!
#140
0!
1-
b0000000000000001 3
12
#141
1!
b001 ;
1%
#142
0!
#143
1!
02
1.
0%
12
b000000000000000000000001 1
#144
0!
#145
1!
b001 <
0.
1%
#146
0!
02
#147
1!
1.
0%
12
b000000000000000000000010 1
#148
0!
#149
1!
b001 =
0.
1%
#150
0!
02
#151
1!
1.
0%
12
b000000000000000000000011 1
#152
0!
#153
1!
b001 >
0.
1%
#154
0!
02
#155
1!
1.
0%
12
b000000000000000000000100 1
#156
0!
#157
1!
b001 ?
0.
1%
#158
0!
02
#159
1!
1.
0%
0-
b000000000000000001111000 1
b0000000000010111 3
#160
0!
#161
1!
b000000000000000001111000 4
b0000000000010111 7
0.
#162
0!
#163
1!
#164
0!
12
#165
1!
16
